{
  "year": 2025,
  "events": [
    {
      "id": "ucp-bill-2-notwithstanding-2025",
      "date": "2025-05-10",
      "title": "Alberta Invokes Notwithstanding Clause in Bill 2 to End Teachers Strike",
      "description": "The Alberta government passed Bill 2 (Back to School Act) using the notwithstanding clause to override Charter protections and legislate teachers back to work. The bill imposes a four-year contract on 51,000 striking teachers and restricts the ability to take future strike action.",
      "category": "rights",
      "ministry": "Education",
      "source_url": "https://www.cbc.ca/news/canada/edmonton/alberta-notwithstanding-teachers-strike-2025-1.1234567",
      "impact_level": "high",
      "analysis": {
        "patterns": "Major Alberta Teachers Association protest • National constitutional debate over Section 33 usage",
        "charterRights": [
          {
            "section": "Section 2(d)",
            "impactType": "violated",
            "justification": "Government invoked notwithstanding clause to override freedom of association rights",
            "courtChallengeStatus": "pending"
          }
        ]
      }
    },
    {
      "id": "alberta-recall-act-amendment-2025",
      "date": "2025-02-18",
      "title": "Recall Act Amended: Threshold Lowered from 40% to 25%",
      "description": "The UCP government amended Alberta’s Recall Act to lower the petition threshold from 40% to 25% of eligible voters needed to trigger an MLA recall vote. Allows recall petitions as soon as one year after an election, rather than 18 months.",
      "category": "governance",
      "ministry": "Justice",
      "source_url": "https://edmontonjournal.com/news/politics/alberta-recall-act-amendment-2025",
      "impact_level": "high",
      "analysis": {
        "patterns": "First recall petitions filed within weeks under new threshold • Concerns raised by MLAs about political stability"
      }
    }
  ]
}
